openweather_report/__init__.py
openweather_report/__main__.py
openweather_report/cli.py
openweather_report/duckdb.py
openweather_report/openweather.py
openweather_report/openweather.sql
openweather_report/postgres.py
openweather_report/sqlite.py
openweather_report-0.3.1.dist-info/METADATA
openweather_report-0.3.1.dist-info/WHEEL
openweather_report-0.3.1.dist-info/entry_points.txt
openweather_report-0.3.1.dist-info/licenses/LICENSE
openweather_report-0.3.1.dist-info/RECORD
