Metadata-Version: 2.4
Name: openweather_report
Version: 0.3.1
Dynamic: Summary
Project-URL: Documentation, https://github.com/cetyler/openweather_report/wiki
Project-URL: Source, https://github.com/cetyler/openweather_report/wiki
Author: Christopher Tyler
Maintainer: Christopher Tyler
License: The MIT License (MIT)
License-File: LICENSE
Classifier: License :: OSI Approved :: MIT License
Requires-Python: >=3.11
Requires-Dist: aiosql>=8.0
Requires-Dist: click>=8.1
Requires-Dist: duckdb>=1.1.3
Requires-Dist: psycopg2>=2.9
Requires-Dist: requests>=2.28
